dtcc_builder/__init__.py
dtcc_builder/_dtcc_builder.cp312-win32.pyd
dtcc_builder/_PointCloud.py
dtcc_builder/builders.py
dtcc_builder/city_methods.py
dtcc_builder/logging.py
dtcc_builder/meshing.py
dtcc_builder/model.py
dtcc_builder/parameters.py
dtcc_builder/scripts/__init__.py
dtcc_builder/scripts/dtcc_build.py
dtcc_builder-0.7.21.dist-info/METADATA
dtcc_builder-0.7.21.dist-info/WHEEL
dtcc_builder-0.7.21.dist-info/entry_points.txt
dtcc_builder-0.7.21.dist-info/licenses/LICENSE
dtcc_builder-0.7.21.dist-info/RECORD
