Metadata-Version: 2.1
Name: dtcc-builder
Version: 0.7.21
Summary: DTCC Builder
Author-Email: Anders Logg <logg@chalmers.se>, Vasilis Naserentin <vasilis.naserentin@chalmers.se>, Dag Wästberg <dwastberg@gmail.com>, George Spaias <gspaiasa@ece.auth.gr>, Jens Olsson <jens.olsson@chalmersindustriteknik.se>
Classifier: Intended Audience :: Science/Research
Classifier: Programming Language :: Python :: 3
Classifier: Programming Language :: C++
Classifier: License :: OSI Approved :: MIT License
Requires-Python: >=3.10
Requires-Dist: pybind11<2.11.0,>=2.10.0
Requires-Dist: numpy
Requires-Dist: dtcc-model>=0.7.21
Requires-Dist: dtcc-io>=0.7.21
Requires-Dist: dtcc-wrangler>=0.7.21
Requires-Dist: dtcc-common>=0.7.21
Requires-Dist: pytest; extra == "test"
Provides-Extra: test
